bvbrc/RQL.py
bvbrc/__init__.py
bvbrc/_api.py
bvbrc/_utils.py
bvbrc/errors.py
bvbrc/response.py
bvbrc/return_format.py
bvbrc/client/__init__.py
bvbrc/client/antibiotics.py
bvbrc/client/bioset.py
bvbrc/client/bioset_result.py
bvbrc/client/client.py
bvbrc/client/enzyme_class_ref.py
bvbrc/client/epitope.py
bvbrc/client/epitope_assay.py
bvbrc/client/experiment.py
bvbrc/client/feature_sequence.py
bvbrc/client/gene_ontology_ref.py
bvbrc/client/genome.py
bvbrc/client/genome_amr.py
bvbrc/client/genome_feature.py
bvbrc/client/genome_sequence.py
bvbrc/client/id_ref.py
bvbrc/client/misc_niaid_sgc.py
bvbrc/client/pathway.py
bvbrc/client/pathway_ref.py
bvbrc/client/ppi.py
bvbrc/client/protein_family_ref.py
bvbrc/client/protein_feature.py
bvbrc/client/protein_structure.py
bvbrc/client/sequence_feature.py
bvbrc/client/sequence_feature_vt.py
bvbrc/client/serology.py
bvbrc/client/sp_gene.py
bvbrc/client/sp_gene_ref.py
bvbrc/client/spike_lineage.py
bvbrc/client/spike_variant.py
bvbrc/client/strain.py
bvbrc/client/structured_assertion.py
bvbrc/client/subsystem.py
bvbrc/client/subsystem_ref.py
bvbrc/client/surveillance.py
bvbrc/client/taxonomy.py
bvbrc-0.2.1.dist-info/METADATA
bvbrc-0.2.1.dist-info/WHEEL
bvbrc-0.2.1.dist-info/licenses/LICENSE
bvbrc-0.2.1.dist-info/RECORD
