Metadata-Version: 2.4
Name: bvbrc
Version: 0.2.1
Summary: A python interface to the BV-BRC Data API
Project-URL: documentation, https://bvbrc.readthedocs.io
Project-URL: soure, https://github.com/abates20/bvbrc
Project-URL: issues, https://github.com/abates20/bvbrc/issues
Author-email: Adam Bates <adambates923@gmail.com>
License-Expression: MIT
License-File: LICENSE
Keywords: BV-BRC
Classifier: Development Status :: 4 - Beta
Classifier: Programming Language :: Python :: 3
Classifier: Programming Language :: Python :: 3.9
Classifier: Programming Language :: Python :: 3.10
Classifier: Programming Language :: Python :: 3.11
Requires-Python: >=3.9
Requires-Dist: requests>=2.32.3
Provides-Extra: docs
Requires-Dist: sphinx-tabs>=3.4.7; extra == 'docs'
Requires-Dist: sphinx>=7.4.7; extra == 'docs'
Requires-Dist: sphinxawesome-theme>=5.3.2; extra == 'docs'
